src/__init__.py
src/certifier.py
src/certifier_client.py
src/cli.py
src/constants.py
src/error.py
src/log.py
src/main.py
src/property.py
src/xpki_client.py
src/resources/__init__.py
src/resources/libcertifier-cert.crt
src/resources/libcertifier.cfg
src/resources/seed.p12
src/resources/seedtest.p12
libcertifier-1.1.2.dist-info/LICENSE
libcertifier-1.1.2.dist-info/METADATA
libcertifier-1.1.2.dist-info/WHEEL
libcertifier-1.1.2.dist-info/entry_points.txt
libcertifier-1.1.2.dist-info/top_level.txt
libcertifier-1.1.2.dist-info/RECORD
