Metadata-Version: 2.1
Name: libcertifier
Version: 1.1.2
Summary: CLI to request xPKI certificates
Author: Russell Benjamin
Author-email: russell_benjamin@comcast.com
License: Apache-2.0
License-File: LICENSE
Requires-Dist: base58==2.1.1
Requires-Dist: certifi==2024.8.30
Requires-Dist: cffi==1.17.1
Requires-Dist: charset-normalizer==3.4.0
Requires-Dist: cryptography==43.0.1
Requires-Dist: idna==3.10
Requires-Dist: packaging==24.1
Requires-Dist: psutil==6.0.0
Requires-Dist: requests==2.32.3
Requires-Dist: requests-toolbelt==1.0.0
Requires-Dist: setuptools==75.2.0
Requires-Dist: urllib3==2.2.3
Provides-Extra: dev
Requires-Dist: twine>=5.1.1; extra == "dev"
